home_assistant_bluetooth/__init__.py
home_assistant_bluetooth/py.typed
home_assistant_bluetooth-2.0.0.dist-info/LICENSE
home_assistant_bluetooth-2.0.0.dist-info/METADATA
home_assistant_bluetooth-2.0.0.dist-info/WHEEL
home_assistant_bluetooth-2.0.0.dist-info/RECORD
