Metadata-Version: 2.3
Name: home-assistant-bluetooth
Version: 2.0.0
Summary: Home Assistant Bluetooth Models and Helpers
License: Apache-2.0
Author: J. Nick Koston
Author-email: nick@home-assistant.io
Requires-Python: >=3.11
Classifier: Development Status :: 5 - Production/Stable
Classifier: Intended Audience :: Developers
Classifier: License :: OSI Approved :: Apache Software License
Classifier: Natural Language :: English
Classifier: Operating System :: OS Independent
Classifier: Programming Language :: Python :: 3
Classifier: Programming Language :: Python :: 3.11
Classifier: Programming Language :: Python :: 3.12
Classifier: Programming Language :: Python :: 3.13
Classifier: Topic :: Software Development :: Libraries
Requires-Dist: habluetooth (>=4.0)
Project-URL: Bug Tracker, https://github.com/home-assistant-libs/home-assistant-bluetooth/issues
Project-URL: Changelog, https://github.com/home-assistant-libs/home-assistant-bluetooth/blob/main/CHANGELOG.md
Project-URL: Repository, https://github.com/home-assistant-libs/home-assistant-bluetooth
